tasknode/__init__.py
tasknode/auth.py
tasknode/cli.py
tasknode/constants.py
tasknode/tasks.py
tasknode/utils.py
tasknode-0.0.28.dist-info/METADATA
tasknode-0.0.28.dist-info/WHEEL
tasknode-0.0.28.dist-info/entry_points.txt
tasknode-0.0.28.dist-info/licenses/LICENSE
tasknode-0.0.28.dist-info/RECORD
