Metadata-Version: 2.3
Name: tasknode
Version: 0.0.28
Summary: TaskNode CLI tool for running Python scripts in the cloud
Author-email: Daniel Newman <daniel@tasknode.dev>
Requires-Python: >=3.9
Requires-Dist: pyjwt>=2.10.0
Requires-Dist: requests>=2.32.0
Requires-Dist: typer>=0.13.1
